cvds/__init__.py
cvds/image/__init__.py
cvds/image/meanstd.py
cvds/label/__init__.py
cvds/label/seg.py
cvds-0.0.1.dist-info/METADATA
cvds-0.0.1.dist-info/WHEEL
cvds-0.0.1.dist-info/licence
cvds-0.0.1.dist-info/top_level.txt
cvds-0.0.1.dist-info/RECORD
