Metadata-Version: 2.1
Name: cvds
Version: 0.0.1
Summary: Dataset statistical calculation.
Home-page: https://github.com/geoyee/datastate
Author: geoyee
Author-email: geoyee@yeah.net
License: UNKNOWN
Platform: UNKNOWN
Classifier: Programming Language :: Python :: 3
Classifier: License :: OSI Approved :: MIT License
Requires-Dist: numpy
Requires-Dist: typing
